autoReRun.py
autoReRun-1.3.0.dist-info/METADATA
autoReRun-1.3.0.dist-info/WHEEL
autoReRun-1.3.0.dist-info/top_level.txt
autoReRun-1.3.0.dist-info/RECORD
