Metadata-Version: 2.1
Name: autoReRun
Version: 1.3.0
Summary: A simple program to automatically kill running process(es) and re-spawn new process(es) for the runnable files everytime some specified file(s) get modified (or deleted or created). For example, Automatically re-starting any server when the server file(s) is modified.
Author-email: Bhindi <bhaskarpanja93@gmail.com>
Project-URL: Homepage, https://github.com/BhaskarPanja93/autoReRun
Keywords: auto rerun,auto run,file runner,update,updater
Classifier: License :: OSI Approved :: MIT License
Classifier: Programming Language :: Python
Classifier: Programming Language :: Python :: 3
Requires-Python: >=3.6
Requires-Dist: customisedLogs
